Metadata-Version: 2.1
Name: hide-warnings
Version: 0.17
Summary: This is a python module that can hide any annoying warning messages from external C and C++ libraries in your python project
Home-page: https://github.com/Rainbow-Dreamer/hide_warnings
Author: Rainbow-Dreamer
Author-email: 1036889495@qq.com
License: LGPLv2.1
Download-URL: https://github.com/Rainbow-Dreamer/hide_warnings/archive/0.17.tar.gz
Keywords: python,hide warnings
Platform: UNKNOWN
Classifier: Development Status :: 3 - Alpha
Classifier: Intended Audience :: Developers
Classifier: Topic :: Software Development :: Build Tools
Classifier: License :: OSI Approved :: GNU Lesser General Public License v2 or later (LGPLv2+)
Classifier: Programming Language :: Python :: 3.6
Classifier: Programming Language :: Python :: 3.7
Classifier: Programming Language :: Python :: 3.8
Classifier: Programming Language :: Python :: 3.9
Classifier: Programming Language :: Python :: 3.10
